text_analysis_helpers/__init__.py
text_analysis_helpers/cli.py
text_analysis_helpers/downloaders.py
text_analysis_helpers/exceptions.py
text_analysis_helpers/helpers.py
text_analysis_helpers/html.py
text_analysis_helpers/keywords/__init__.py
text_analysis_helpers/keywords/rake.py
text_analysis_helpers/models.py
text_analysis_helpers/processors/__init__.py
text_analysis_helpers/processors/html.py
text_analysis_helpers/processors/text.py
text_analysis_helpers/text.py
text_analysis_helpers-0.6.0.dist-info/LICENSE
text_analysis_helpers-0.6.0.dist-info/METADATA
text_analysis_helpers-0.6.0.dist-info/WHEEL
text_analysis_helpers-0.6.0.dist-info/entry_points.txt
text_analysis_helpers-0.6.0.dist-info/RECORD
