Metadata-Version: 2.1
Name: text-analysis-helpers
Version: 0.6.0
Summary: Collection of classes and functions for text analysis
Home-page: https://github.com/pmatigakis/text-analysis-helpers
License: MIT
Keywords: text analysis
Author: Matigakis Panagiotis
Author-email: pmatigakis@gmail.com
Requires-Python: >=3.10,<4.0
Classifier: Development Status :: 3 - Alpha
Classifier: Intended Audience :: Developers
Classifier: License :: OSI Approved :: MIT License
Classifier: Natural Language :: English
Classifier: Operating System :: OS Independent
Classifier: Programming Language :: Python :: 3
Classifier: Programming Language :: Python :: 3.10
Classifier: Programming Language :: Python :: 3.11
Classifier: Programming Language :: Python :: 3
Requires-Dist: arrow (>=0.15.5,<1.0.0)
Requires-Dist: article-extraction (>=0.3.0,<0.4.0)
Requires-Dist: extruct (>=0.13.0,<1.0.0)
Requires-Dist: nltk (>=3.3,<4.0)
Requires-Dist: numpy (>=1.15.2,<2.0.0)
Requires-Dist: requests (>=2.26.0,<3.0.0)
Requires-Dist: sumy (>=0.11.0,<1.0.0)
Requires-Dist: textstat (>=0.7.3,<1.0.0)
Project-URL: Repository, https://github.com/pmatigakis/text-analysis-helpers
